rfc7464/__init__.py
rfc7464/_version.py
rfc7464/impl.py
rfc7464/tests/__init__.py
rfc7464/tests/nitpicker.py
rfc7464/tests/test_rfc7464.py
rfc7464-17.7.0.dist-info/DESCRIPTION.rst
rfc7464-17.7.0.dist-info/METADATA
rfc7464-17.7.0.dist-info/RECORD
rfc7464-17.7.0.dist-info/WHEEL
rfc7464-17.7.0.dist-info/metadata.json
rfc7464-17.7.0.dist-info/top_level.txt
