Metadata-Version: 2.0
Name: rfc7464
Version: 17.7.0
Summary: Implementation of RFC7464 codec
Home-page: https://github.com/moshez/rfc7464
Author: Moshe Zadka
Author-email: zadka.moshe@gmail.com
License: MIT
Platform: UNKNOWN
